Metadata-Version: 2.1
Name: odoo-addon-stock_picking_type_force_move_type
Version: 18.0.1.0.1.3
Requires-Python: >=3.10
Requires-Dist: odoo==18.0.*
Summary: Force shipping policies on operation types
Home-page: https://github.com/OCA/stock-logistics-workflow
License: AGPL-3
Author: Camptocamp, Odoo Community Association (OCA)
Author-email: support@odoo-community.org
Classifier: Programming Language :: Python
Classifier: Framework :: Odoo
Classifier: Framework :: Odoo :: 18.0
Classifier: License :: OSI Approved :: GNU Affero General Public License v3
Classifier: Development Status :: 5 - Production/Stable
